HuimaoPythonZhilv/README.md
HuimaoPythonZhilv/__init__.py
HuimaoPythonZhilv/__main__.py
HuimaoPythonZhilv/file.epub
HuimaoPythonZhilv/index.html
HuimaoPythonZhilv/css/__init__.py
HuimaoPythonZhilv/css/annotations.css
HuimaoPythonZhilv/css/main.css
HuimaoPythonZhilv/css/normalize.css
HuimaoPythonZhilv/css/popup.css
HuimaoPythonZhilv/font/__init__.py
HuimaoPythonZhilv/font/fontello.eot
HuimaoPythonZhilv/font/fontello.svg
HuimaoPythonZhilv/font/fontello.ttf
HuimaoPythonZhilv/font/fontello.woff
HuimaoPythonZhilv/img/__init__.py
HuimaoPythonZhilv/img/annotator-glyph-sprite.png
HuimaoPythonZhilv/img/annotator-icon-sprite.png
HuimaoPythonZhilv/img/apple-touch-icon.png
HuimaoPythonZhilv/img/cancelfullscreen.png
HuimaoPythonZhilv/img/close.png
HuimaoPythonZhilv/img/fullscreen.png
HuimaoPythonZhilv/img/loader.gif
HuimaoPythonZhilv/img/menu-icon.png
HuimaoPythonZhilv/img/save.png
HuimaoPythonZhilv/img/saved.png
HuimaoPythonZhilv/img/settings-s.png
HuimaoPythonZhilv/img/settings.png
HuimaoPythonZhilv/img/star.png
HuimaoPythonZhilv/js/__init__.py
HuimaoPythonZhilv/js/epub.js
HuimaoPythonZhilv/js/epub.min.js
HuimaoPythonZhilv/js/epub.min.map
HuimaoPythonZhilv/js/hooks.min.js
HuimaoPythonZhilv/js/hooks.min.map
HuimaoPythonZhilv/js/reader.js
HuimaoPythonZhilv/js/reader.js.map
HuimaoPythonZhilv/js/reader.min.js
HuimaoPythonZhilv/js/reader.min.map
HuimaoPythonZhilv/js/hooks/__init__.py
HuimaoPythonZhilv/js/hooks/extensions/__init__.py
HuimaoPythonZhilv/js/hooks/extensions/highlight.js
HuimaoPythonZhilv/js/libs/__init__.py
HuimaoPythonZhilv/js/libs/jquery.min.js
HuimaoPythonZhilv/js/libs/localforage.min.js
HuimaoPythonZhilv/js/libs/screenfull.js
HuimaoPythonZhilv/js/libs/screenfull.min.js
HuimaoPythonZhilv/js/libs/zip.min.js
HuimaoPythonZhilv/js/plugins/__init__.py
HuimaoPythonZhilv/js/plugins/hypothesis.js
HuimaoPythonZhilv/js/plugins/search.js
huimao_python_zhilv-2024.3.2.0.dist-info/METADATA
huimao_python_zhilv-2024.3.2.0.dist-info/WHEEL
huimao_python_zhilv-2024.3.2.0.dist-info/entry_points.txt
huimao_python_zhilv-2024.3.2.0.dist-info/top_level.txt
huimao_python_zhilv-2024.3.2.0.dist-info/RECORD
